tinyexp/__init__.py
tinyexp/exceptions.py
tinyexp/dataset/__init__.py
tinyexp/dataset/fake_dataloader.py
tinyexp/dataset/sampler.py
tinyexp/examples/__init__.py
tinyexp/examples/mnist_exp.py
tinyexp/examples/resnet_exp.py
tinyexp/tiny_engine/accelerator/__init__.py
tinyexp/tiny_engine/accelerator/base_accelerator.py
tinyexp/tiny_engine/accelerator/cpu_accelerator.py
tinyexp/tiny_engine/accelerator/ddp_accelerator.py
tinyexp/tiny_engine/accelerator/hf_accelerator.py
tinyexp/utils/__init__.py
tinyexp/utils/log_utils.py
tinyexp/utils/model_utils.py
tinyexp/utils/ray_utils.py
tinyexp/utils/redis_utils.py
tinyexp-0.0.2.dist-info/METADATA
tinyexp-0.0.2.dist-info/WHEEL
tinyexp-0.0.2.dist-info/licenses/LICENSE
tinyexp-0.0.2.dist-info/RECORD
