Metadata-Version: 2.4
Name: TinyExp
Version: 0.0.2
Summary: A minimalist Python project for deep learning experiment management. It uses Ray for core distributed environment and backend setup, and provides basic, no-frills tracking for models, optimizers, and LR schedulers.
Project-URL: Homepage, https://zengarden.github.io/TinyExp/
Project-URL: Repository, https://github.com/zengarden/TinyExp
Project-URL: Documentation, https://zengarden.github.io/TinyExp/
Author-email: Zeming LI <zane.li@connect.ust.hk>
License: MIT License
License-File: LICENSE
Keywords: python
Classifier: Intended Audience :: Developers
Classifier: License :: OSI Approved :: MIT License
Classifier: Programming Language :: Python
Classifier: Programming Language :: Python :: 3
Classifier: Programming Language :: Python :: 3.9
Classifier: Programming Language :: Python :: 3.10
Classifier: Programming Language :: Python :: 3.11
Classifier: Programming Language :: Python :: 3.12
Classifier: Programming Language :: Python :: 3.13
Classifier: Topic :: Software Development :: Libraries :: Python Modules
Requires-Python: <4.0,>=3.9
Requires-Dist: accelerate
Requires-Dist: hydra-core
Requires-Dist: loguru
Requires-Dist: loguru>=0.7.3
Requires-Dist: numpy
Requires-Dist: omegaconf
Requires-Dist: ray
Requires-Dist: redis
Requires-Dist: tabulate
Requires-Dist: torch
Requires-Dist: torchvision
Requires-Dist: tqdm
Requires-Dist: wandb
